utcp/__init__.py
utcp/utcp_client.py
utcp/data/__init__.py
utcp/data/auth.py
utcp/data/call_template.py
utcp/data/register_manual_response.py
utcp/data/tool.py
utcp/data/utcp_client_config.py
utcp/data/utcp_manual.py
utcp/data/variable_loader.py
utcp/data/auth_implementations/__init__.py
utcp/data/auth_implementations/api_key_auth.py
utcp/data/auth_implementations/basic_auth.py
utcp/data/auth_implementations/oauth2_auth.py
utcp/data/variable_loader_implementations/__init__.py
utcp/data/variable_loader_implementations/dot_env_variable_loader.py
utcp/exceptions/__init__.py
utcp/exceptions/utcp_serializer_validation_error.py
utcp/exceptions/utcp_variable_not_found_exception.py
utcp/implementations/__init__.py
utcp/implementations/default_variable_substitutor.py
utcp/implementations/in_mem_tool_repository.py
utcp/implementations/tag_search.py
utcp/implementations/utcp_client_implementation.py
utcp/implementations/post_processors/__init__.py
utcp/implementations/post_processors/filter_dict_post_processor.py
utcp/implementations/post_processors/limit_strings_post_processor.py
utcp/interfaces/__init__.py
utcp/interfaces/communication_protocol.py
utcp/interfaces/concurrent_tool_repository.py
utcp/interfaces/serializer.py
utcp/interfaces/tool_post_processor.py
utcp/interfaces/tool_search_strategy.py
utcp/interfaces/variable_substitutor.py
utcp/plugins/__init__.py
utcp/plugins/discovery.py
utcp/plugins/plugin_loader.py
utcp/python_specific_tooling/__init__.py
utcp/python_specific_tooling/async_rwlock.py
utcp/python_specific_tooling/tool_decorator.py
utcp/python_specific_tooling/version.py
utcp-1.0.4.dist-info/METADATA
utcp-1.0.4.dist-info/WHEEL
utcp-1.0.4.dist-info/top_level.txt
utcp-1.0.4.dist-info/RECORD
