Metadata-Version: 2.4
Name: utcp
Version: 1.0.4
Summary: Universal Tool Calling Protocol (UTCP) client library for Python
Author: UTCP Contributors
License-Expression: MPL-2.0
Project-URL: Homepage, https://utcp.io
Project-URL: Source, https://github.com/universal-tool-calling-protocol/python-utcp
Project-URL: Issues, https://github.com/universal-tool-calling-protocol/python-utcp/issues
Classifier: Development Status :: 4 - Beta
Classifier: Intended Audience :: Developers
Classifier: Programming Language :: Python :: 3
Classifier: Operating System :: OS Independent
Requires-Python: >=3.10
Requires-Dist: pydantic>=2.0
Requires-Dist: python-dotenv>=1.0
Requires-Dist: tomli>=2.0
Provides-Extra: dev
Requires-Dist: build; extra == "dev"
Requires-Dist: pytest; extra == "dev"
Requires-Dist: pytest-asyncio; extra == "dev"
Requires-Dist: pytest-cov; extra == "dev"
Requires-Dist: coverage; extra == "dev"
Requires-Dist: twine; extra == "dev"
